{
  "question": "What was the score in round 11 of the 2018 RFL League 1 results when the away team has a skull on its logo?",
  "image_path": [
    "/Users/ashishrajshekhar/Desktop/CORAL LAB/ADAF/data/mmqa/final_dataset_images/1831b2fdecfbd1064427cddbccb887cf"
  ],
  "table": [
    {
      "table_rows": [
        [
          {
            "text": "Hemel Stags",
            "links": [
              {
                "text": "Hemel Stags",
                "wiki_title": "Hemel Stags",
                "url": "https://en.wikipedia.org/wiki/Hemel_Stags"
              }
            ]
          },
          {
            "text": "0\u201368",
            "links": []
          },
          {
            "text": "Bradford Bulls",
            "links": [
              {
                "text": "Bradford Bulls",
                "wiki_title": "Bradford Bulls",
                "url": "https://en.wikipedia.org/wiki/Bradford_Bulls"
              }
            ]
          },
          {
            "text": "27 May 2018, 14:00",
            "links": []
          },
          {
            "text": "Pennine Way Stadium",
            "links": [
              {
                "text": "Pennine Way Stadium",
                "wiki_title": "Pennine Way Stadium",
                "url": "https://en.wikipedia.org/wiki/Pennine_Way_Stadium"
              }
            ]
          },
          {
            "text": "M. Mannifield",
            "links": []
          },
          {
            "text": "736",
            "links": []
          }
        ],
        [
          {
            "text": "North Wales Crusaders",
            "links": [
              {
                "text": "North Wales Crusaders",
                "wiki_title": "North Wales Crusaders",
                "url": "https://en.wikipedia.org/wiki/North_Wales_Crusaders"
              }
            ]
          },
          {
            "text": "42\u20136",
            "links": []
          },
          {
            "text": "Coventry Bears",
            "links": [
              {
                "text": "Coventry Bears",
                "wiki_title": "Coventry Bears",
                "url": "https://en.wikipedia.org/wiki/Coventry_Bears"
              }
            ]
          },
          {
            "text": "27 May 2018, 14:30",
            "links": []
          },
          {
            "text": "Queensway Stadium",
            "links": [
              {
                "text": "Queensway Stadium",
                "wiki_title": "Queensway Stadium",
                "url": "https://en.wikipedia.org/wiki/Queensway_Stadium"
              }
            ]
          },
          {
            "text": "N. Bennett",
            "links": []
          },
          {
            "text": "301",
            "links": []
          }
        ],
        [
          {
            "text": "Hunslet",
            "links": [
              {
                "text": "Hunslet",
                "wiki_title": "Hunslet R.L.F.C.",
                "url": "https://en.wikipedia.org/wiki/Hunslet_R.L.F.C."
              }
            ]
          },
          {
            "text": "86\u20130",
            "links": []
          },
          {
            "text": "West Wales Raiders",
            "links": [
              {
                "text": "West Wales Raiders",
                "wiki_title": "West Wales Raiders",
                "url": "https://en.wikipedia.org/wiki/West_Wales_Raiders"
              }
            ]
          },
          {
            "text": "27 May 2018, 15:00",
            "links": []
          },
          {
            "text": "South Leeds Stadium",
            "links": [
              {
                "text": "South Leeds Stadium",
                "wiki_title": "South Leeds Stadium",
                "url": "https://en.wikipedia.org/wiki/South_Leeds_Stadium"
              }
            ]
          },
          {
            "text": "B. Pearson",
            "links": []
          },
          {
            "text": "415",
            "links": []
          }
        ],
        [
          {
            "text": "Keighley Cougars",
            "links": [
              {
                "text": "Keighley Cougars",
                "wiki_title": "Keighley Cougars",
                "url": "https://en.wikipedia.org/wiki/Keighley_Cougars"
              }
            ]
          },
          {
            "text": "26\u201318",
            "links": []
          },
          {
            "text": "London Skolars",
            "links": [
              {
                "text": "London Skolars",
                "wiki_title": "London Skolars",
                "url": "https://en.wikipedia.org/wiki/London_Skolars"
              }
            ]
          },
          {
            "text": "27 May 2018, 15:00",
            "links": []
          },
          {
            "text": "Cougar Park",
            "links": [
              {
                "text": "Cougar Park",
                "wiki_title": "Cougar Park",
                "url": "https://en.wikipedia.org/wiki/Cougar_Park"
              }
            ]
          },
          {
            "text": "J. McMullen",
            "links": []
          },
          {
            "text": "521",
            "links": []
          }
        ],
        [
          {
            "text": "Oldham",
            "links": [
              {
                "text": "Oldham",
                "wiki_title": "Oldham R.L.F.C.",
                "url": "https://en.wikipedia.org/wiki/Oldham_R.L.F.C."
              }
            ]
          },
          {
            "text": "32\u201312",
            "links": []
          },
          {
            "text": "Doncaster",
            "links": [
              {
                "text": "Doncaster",
                "wiki_title": "Doncaster R.L.F.C.",
                "url": "https://en.wikipedia.org/wiki/Doncaster_R.L.F.C."
              }
            ]
          },
          {
            "text": "3 June 2018, 15:00",
            "links": []
          },
          {
            "text": "Whitebank Stadium",
            "links": [
              {
                "text": "Whitebank Stadium",
                "wiki_title": "Whitebank Stadium",
                "url": "https://en.wikipedia.org/wiki/Whitebank_Stadium"
              }
            ]
          },
          {
            "text": "J. McMullen",
            "links": []
          },
          {
            "text": "453",
            "links": []
          }
        ],
        [
          {
            "text": "Whitehaven",
            "links": [
              {
                "text": "Whitehaven",
                "wiki_title": "Whitehaven R.L.F.C.",
                "url": "https://en.wikipedia.org/wiki/Whitehaven_R.L.F.C."
              }
            ]
          },
          {
            "text": "26\u201318",
            "links": []
          },
          {
            "text": "York City Knights",
            "links": [
              {
                "text": "York City Knights",
                "wiki_title": "York City Knights",
                "url": "https://en.wikipedia.org/wiki/York_City_Knights"
              }
            ]
          },
          {
            "text": "27 May 2018, 15:00",
            "links": []
          },
          {
            "text": "Recreation Ground",
            "links": [
              {
                "text": "Recreation Ground",
                "wiki_title": "Recreation Ground (Whitehaven)",
                "url": "https://en.wikipedia.org/wiki/Recreation_Ground_(Whitehaven)"
              }
            ]
          },
          {
            "text": "T. Crashley",
            "links": []
          },
          {
            "text": "640",
            "links": []
          }
        ],
        [
          {
            "text": "Workington Town",
            "links": [
              {
                "text": "Workington Town",
                "wiki_title": "Workington Town",
                "url": "https://en.wikipedia.org/wiki/Workington_Town"
              }
            ]
          },
          {
            "text": "38\u201318",
            "links": []
          },
          {
            "text": "Newcastle Thunder",
            "links": [
              {
                "text": "Newcastle Thunder",
                "wiki_title": "Newcastle Thunder",
                "url": "https://en.wikipedia.org/wiki/Newcastle_Thunder"
              }
            ]
          },
          {
            "text": "27 May 2018, 15:00",
            "links": []
          },
          {
            "text": "Derwent Park",
            "links": [
              {
                "text": "Derwent Park",
                "wiki_title": "Derwent Park",
                "url": "https://en.wikipedia.org/wiki/Derwent_Park"
              }
            ]
          },
          {
            "text": "M. Griffiths",
            "links": []
          },
          {
            "text": "696",
            "links": []
          }
        ],
        [
          {
            "text": "Source:",
            "links": [
              {
                "text": "Rugby Leaguer & League Express",
                "wiki_title": "Rugby Leaguer & League Express",
                "url": "https://en.wikipedia.org/wiki/Rugby_Leaguer_&_League_Express"
              }
            ]
          },
          {
            "text": "Source:",
            "links": [
              {
                "text": "Rugby Leaguer & League Express",
                "wiki_title": "Rugby Leaguer & League Express",
                "url": "https://en.wikipedia.org/wiki/Rugby_Leaguer_&_League_Express"
              }
            ]
          },
          {
            "text": "Source:",
            "links": [
              {
                "text": "Rugby Leaguer & League Express",
                "wiki_title": "Rugby Leaguer & League Express",
                "url": "https://en.wikipedia.org/wiki/Rugby_Leaguer_&_League_Express"
              }
            ]
          },
          {
            "text": "Source:",
            "links": [
              {
                "text": "Rugby Leaguer & League Express",
                "wiki_title": "Rugby Leaguer & League Express",
                "url": "https://en.wikipedia.org/wiki/Rugby_Leaguer_&_League_Express"
              }
            ]
          },
          {
            "text": "Source:",
            "links": [
              {
                "text": "Rugby Leaguer & League Express",
                "wiki_title": "Rugby Leaguer & League Express",
                "url": "https://en.wikipedia.org/wiki/Rugby_Leaguer_&_League_Express"
              }
            ]
          },
          {
            "text": "Source:",
            "links": [
              {
                "text": "Rugby Leaguer & League Express",
                "wiki_title": "Rugby Leaguer & League Express",
                "url": "https://en.wikipedia.org/wiki/Rugby_Leaguer_&_League_Express"
              }
            ]
          },
          {
            "text": "Source:",
            "links": [
              {
                "text": "Rugby Leaguer & League Express",
                "wiki_title": "Rugby Leaguer & League Express",
                "url": "https://en.wikipedia.org/wiki/Rugby_Leaguer_&_League_Express"
              }
            ]
          }
        ]
      ],
      "table_name": "Round 11",
      "header": [
        {
          "column_name": "Home",
          "metadata": {
            "num_of_links": 8,
            "ner_appearances_map": {
              "ORG": 1,
              "PERSON": 3,
              "GPE": 1
            },
            "is_key_column": true,
            "image_associated_column": true,
            "entities_column": true
          }
        },
        {
          "column_name": "Score",
          "metadata": {
            "num_of_links": 1,
            "ner_appearances_map": {
              "PERSON": 2
            }
          }
        },
        {
          "column_name": "Away",
          "metadata": {
            "num_of_links": 8,
            "ner_appearances_map": {
              "ORG": 1
            },
            "entities_column": true
          }
        },
        {
          "column_name": "Match Information - Date and Time",
          "metadata": {
            "num_of_links": 1,
            "ner_appearances_map": {
              "DATE": 1
            }
          }
        },
        {
          "column_name": "Match Information - Venue",
          "metadata": {
            "num_of_links": 8,
            "ner_appearances_map": {
              "FAC": 3,
              "PERSON": 2
            },
            "entities_column": true
          }
        },
        {
          "column_name": "Match Information - Referee",
          "metadata": {
            "num_of_links": 1,
            "ner_appearances_map": {
              "PERSON": 7
            }
          }
        },
        {
          "column_name": "Match Information - Attendance",
          "metadata": {
            "num_of_links": 1,
            "ner_appearances_map": {
              "CARDINAL": 6
            }
          }
        }
      ]
    }
  ],
  "context": "",
  "image_cues": "",
  "user_profile": "general"
}