{
  "question": "WRBJ-FM is licensed to which Rankin County, Mississippi town?",
  "image_path": [],
  "table": [],
  "context": "WRBJ-FM (97.7 FM) is an urban contemporary radio station in Jackson, Mississippi, but licensed to Brandon, Mississippi.  The station is owned and operated by Roberts Broadcasting, former owners of The CW television affiliate WRBJ.  Its studios are located at The Roberts Building along State Street in Jackson, just two blocks north of the Mississippi State Capitol building, and the transmitter tower is south of Brandon.\n\nBrandon is a city in Rankin County, Mississippi. The population was 21,705 at the 2010 census. It is the county seat of Rankin County.  Brandon is part of the Jackson Metropolitan Statistical Area and located east of the state capital.",
  "image_cues": "",
  "user_profile": "general"
}